attrd/__init__.py
attrd-0.0.4.dist-info/METADATA
attrd-0.0.4.dist-info/WHEEL
attrd-0.0.4.dist-info/top_level.txt
attrd-0.0.4.dist-info/RECORD
