Metadata-Version: 2.1
Name: attrd
Version: 0.0.4
Summary: Attribute dictionary implementation that allow get access to their elements by keys (as native dict) and attributes.
Home-page: https://pypi.org/project/attrd/
Author: Filantus
Author-email: filantus@mail.ru
License: GPL
Platform: UNKNOWN
Classifier: Intended Audience :: Developers
Classifier: License :: OSI Approved :: GNU General Public License (GPL)
Classifier: Programming Language :: Python :: 3.7
Classifier: Programming Language :: Python :: 3.8
Classifier: Operating System :: OS Independent
